{
  "home": {
    "subtitle": "with Juli Burns",
    "title_line1": "Build perfect body",
    "title_line2": "shape for good and",
    "title_line3": "healthy lifestyle",
    "button": "Join now"
  },
  "about": {
    "title": "About Mobility Moments",
    "paragraph": "Hi, I'm Juli. I have been in the field of physical training for the past 2 years, helping people on the way to achieving their best functional physique and fitness.",
    "additionalParagraph": "I provide a flexible training schedule with a variety of custom online and onsite personal training plans. Get started on your Mobility journey!"
  },
  "services": {
    "title": "My Services",
    "items": [
      {
        "title": "Custom Training",
        "description": "Training plans considering all factors of our valuable clients. From fitting your budget to ensuring perfect time slots, we've got you covered."
      },
      {
        "title": "Real Results",
        "description": "Proven techniques and expert coaching to help you achieve a longer, healthier life. I believe in a no-excuse approach to fitness with guaranteed results."
      },
      {
        "title": "Calculated Nutrition",
        "description": "Personalized, calculated nutrition plans with optimized macros to remove obstacles to your progress."
      }
    ]
  },
  "pricing": {
    "title": "Pricing",
    "plans": [
      {
        "title": "The Enthusiast",
        "price": "$60",
        "description": ["On-call training", "17 sessions per month"]
      },
      {
        "title": "The Visionary",
        "price": "$85",
        "description": ["Video call training", "17 sessions per month"]
      },
      {
        "title": "The Staunch",
        "price": "$120",
        "description": ["12 live on-site sessions per month", "10 video call sessions per month"]
      }
    ]
  },
  "contact": {
    "title": "Contact Information",
    "address": "Ridgecrest CA, 93555",
    "phone": "+7607938987",
    "email": "Mobilitymotion@gmail.com"
  },
  "footer": {
  "left": {
    "description": "Mobility Moments is a personal training service that provides safe and effective custom exercise plans. Your workout plan is unique to you and your goals."
  },
  "center": {
    "heading": "Quick Links",
    "links": [
      { "text": "Home", "href": "#home" },
      { "text": "About", "href": "#about" },
      { "text": "Services", "href": "#services" },
      { "text": "Price", "href": "#price" }
    ]
  },
  "right": {
    "heading": "Address",
    "address": [
      { "icon": "fas fa-map-marker-alt", "text": "Ridgecrest CA, 93555" },
      { "icon": "fas fa-phone", "text": "+7607938987" },
      { "icon": "fas fa-envelope-square", "text": "Mobilitymotion@gmail.com" }
    ]
  },
  "developer": "Developer: Nikhil and Prashant",
  "copyright": " 2024 powered by unenter"
},

  "maps": {
    "heading": "Find Me at 760 Gym",
    "iframeSrc": "https://maps.google.com/maps?q=%20923%20S%20China%20Lake%20Blvd,%20Ridgecrest,%20CA%2093555&t=k&z=13&ie=UTF8&iwloc=&output=embed"
  }
}
